python_mealie_api/__init__.py
python_mealie_api/client/__init__.py
python_mealie_api/client/client.py
python_mealie_api/client/http_client.py
python_mealie_api/client/token_repository.py
python_mealie_api/exception/__init__.py
python_mealie_api/exception/exception.py
python_mealie_api/model/__init__.py
python_mealie_api/model/auth.py
python_mealie_api/model/common.py
python_mealie_api/model/groups.py
python_mealie_api/model/model.py
python_mealie_api/model/recipe.py
python_mealie_api/model/shopping_lists.py
python_mealie_api/model/sign_up.py
python_mealie_api/model/users.py
python_mealie_api-0.0.1a0.dist-info/LICENSE
python_mealie_api-0.0.1a0.dist-info/WHEEL
python_mealie_api-0.0.1a0.dist-info/METADATA
python_mealie_api-0.0.1a0.dist-info/RECORD
