Metadata-Version: 2.1
Name: python-mealie-api
Version: 0.0.1a0
Summary: A python based mealie client
License: MIT
Author: Marvin Straathof
Author-email: marvinstraathof@gmail.com
Requires-Python: >=3.10,<4.0
Classifier: License :: OSI Approved :: MIT License
Classifier: Programming Language :: Python :: 3
Classifier: Programming Language :: Python :: 3.10
Requires-Dist: aiohttp (>=3.8.1,<4.0.0)
Requires-Dist: pydantic (>=1.9.0,<2.0.0)
